incognitus_client/__init__.py
incognitus_client/incognitus.py
incognitus_client-1.0.1.dist-info/LICENSE.md
incognitus_client-1.0.1.dist-info/METADATA
incognitus_client-1.0.1.dist-info/WHEEL
incognitus_client-1.0.1.dist-info/top_level.txt
incognitus_client-1.0.1.dist-info/RECORD
