Metadata-Version: 2.1
Name: incognitus-client
Version: 1.0.1
Summary: Incognitus python client
Home-page: https://github.com/Incognitus-IO/client-python
Author: Incognitus
Author-email: support@incognitus.io
License: MIT
Project-URL: Source, https://github.com/Incognitus-Io/client-python.git
Project-URL: Tracker, https://github.com/Incognitus-IO/client-python/issues
Project-URL: Changelog, https://github.com/Incognitus-IO/client-python/blob/master/CHANGELOG.md
Keywords: feature-flags,feature-toggle,feature,toggle,flags,incognitus
Platform: UNKNOWN
Classifier: Development Status :: 3 - Alpha
Classifier: Programming Language :: Python :: 3
Classifier: License :: OSI Approved :: MIT License
Classifier: Operating System :: OS Independent
Classifier: Topic :: Software Development :: Libraries
Requires-Python: >=3.6
Requires-Dist: requests (>=2.25.0)
